pyip_liumou_Stable/Public4.py
pyip_liumou_Stable/Public6.py
pyip_liumou_Stable/__init__.py
pyip_liumou_Stable/requirements.txt
pyip_liumou_stable-1.0.1.dist-info/METADATA
pyip_liumou_stable-1.0.1.dist-info/WHEEL
pyip_liumou_stable-1.0.1.dist-info/licenses/LICENSE
pyip_liumou_stable-1.0.1.dist-info/RECORD
